data_fingerprint/__init___.py
data_fingerprint/src/__init__.py
data_fingerprint/src/checkers.py
data_fingerprint/src/comparator.py
data_fingerprint/src/difference_types.py
data_fingerprint/src/models.py
data_fingerprint/src/utils.py
data_fingerprint-0.1.10.dist-info/LICENCE.txt
data_fingerprint-0.1.10.dist-info/METADATA
data_fingerprint-0.1.10.dist-info/WHEEL
data_fingerprint-0.1.10.dist-info/RECORD
