Metadata-Version: 2.3
Name: data-fingerprint
Version: 0.1.10
Summary: DataFingerprint is a Python package designed to compare two datasets and generate a detailed report highlighting the differences between them. This tool is particularly useful for data validation, quality assurance, and ensuring data consistency across different sources.
Author: SimpleSimpler
Requires-Python: >=3.12,<4.0
Classifier: Programming Language :: Python :: 3
Classifier: Programming Language :: Python :: 3.12
Classifier: Programming Language :: Python :: 3.13
Requires-Dist: pandas (>=2.2.3,<3.0.0)
Requires-Dist: pdoc (>=15.0.1,<16.0.0)
Requires-Dist: polars (>=1.26.0,<2.0.0)
Requires-Dist: pyarrow (>=19.0.1,<20.0.0)
Requires-Dist: pydantic (>=2.11.0,<3.0.0)
Requires-Dist: pytest (>=8.3.5,<9.0.0)
